sensoterra/__init__.py
sensoterra/customerapi.py
sensoterra/probe.py
sensoterra/py.typed
sensoterra-2.0.1.dist-info/LICENSE
sensoterra-2.0.1.dist-info/METADATA
sensoterra-2.0.1.dist-info/WHEEL
sensoterra-2.0.1.dist-info/top_level.txt
sensoterra-2.0.1.dist-info/RECORD
