Metadata-Version: 2.1
Name: sensoterra
Version: 2.0.1
Summary: Query Sensoterra probes using the Customer API
Author-email: Mark Ruys <mark.ruys@sensoterra.com>
Project-URL: Homepage, https://gitlab.com/sensoterra/public/python
Project-URL: Issues, https://gitlab.com/sensoterra/public/python/-/issues
Project-URL: Repository, https://gitlab.com/sensoterra/public/python.git
Project-URL: Changelog, https://gitlab.com/sensoterra/public/python/-/blob/main/CHANGELOG.md
Keywords: Sensoterra,soil moisture,probe,sensor
Classifier: Programming Language :: Python :: 3
Classifier: License :: OSI Approved :: MIT License
Classifier: Operating System :: OS Independent
Classifier: Intended Audience :: Developers
Classifier: Development Status :: 5 - Production/Stable
Requires-Python: >=3.11
License-File: LICENSE
Requires-Dist: requests>=2.27.1
